mobgap/__init__.py
mobgap/_docutils.py
mobgap/consts.py
mobgap/plotting.py
mobgap/_gaitmap/.ruff.toml
mobgap/_gaitmap/__init__.py
mobgap/_gaitmap/trajectory_reconstruction/__init__.py
mobgap/_gaitmap/trajectory_reconstruction/orientation_methods/__init__.py
mobgap/_gaitmap/trajectory_reconstruction/orientation_methods/_madgwick.py
mobgap/_gaitmap/utils/__init__.py
mobgap/_gaitmap/utils/array_handling.py
mobgap/_gaitmap/utils/fast_quaternion_math.py
mobgap/_gaitmap/utils/rotations.py
mobgap/_utils_internal/__init__.py
mobgap/_utils_internal/misc.py
mobgap/aggregation/__init__.py
mobgap/aggregation/_mobilised_aggregator.py
mobgap/aggregation/_threshold_check.py
mobgap/aggregation/base.py
mobgap/aggregation/_dmo_thresholds/__init__.py
mobgap/aggregation/_dmo_thresholds/official_mobilised_dmo_thresholds.csv
mobgap/cadence/__init__.py
mobgap/cadence/_cad_from_ic.py
mobgap/cadence/base.py
mobgap/cadence/evaluation.py
mobgap/cadence/pipeline.py
mobgap/data/__init__.py
mobgap/data/_dataset_from_data.py
mobgap/data/_example_data.py
mobgap/data/_example_data_registry.txt
mobgap/data/_mobilised_cvs_dmo_dataset.py
mobgap/data/_mobilised_matlab_loader.py
mobgap/data/_mobilised_tvs_dataset.py
mobgap/data/_mobilsed_weartime_loader.py
mobgap/data/_ms_project.py
mobgap/data/base.py
mobgap/data/validation_results.py
mobgap/data_transform/__init__.py
mobgap/data_transform/_cwt.py
mobgap/data_transform/_filter.py
mobgap/data_transform/_gaussian_filter.py
mobgap/data_transform/_padding.py
mobgap/data_transform/_resample.py
mobgap/data_transform/_savgol_filter.py
mobgap/data_transform/_utils.py
mobgap/data_transform/base.py
mobgap/data_transform/_filter_coeffs/__init__.py
mobgap/data_transform/_filter_coeffs/epfl_gait_filter.csv
mobgap/gait_sequences/__init__.py
mobgap/gait_sequences/_evaluation_scorer.py
mobgap/gait_sequences/_gsd_iluz.py
mobgap/gait_sequences/_gsd_ionescu.py
mobgap/gait_sequences/base.py
mobgap/gait_sequences/evaluation.py
mobgap/gait_sequences/pipeline.py
mobgap-1.0.0.dist-info/METADATA
mobgap-1.0.0.dist-info/WHEEL
mobgap-1.0.0.dist-info/licenses/LICENSE
mobgap-1.0.0.dist-info/licenses/NOTICE
mobgap-1.0.0.dist-info/RECORD
