Metadata-Version: 2.4
Name: mobgap
Version: 1.0.0
Summary: A Python implementation of the Mobilise-D algorithm pipeline for gait analysis using IMU worn at the lower back.
Author-email: Arne Küderle <arne.kuederle@fau.de>, Felix Kluge <felix.kluge@novartis.com>, Paolo Tasca <paolo.tasca@polito.it>, Metin Bicer <metin.bicer@newcastle.ac.uk>, Annika Mücke <annika-muecke@outlook.de>, Dimitrios Megaritis <Dimitris.Megaritis@newcastle.ac.uk>, Zamal Babar <zamalali9866@gmail.com>, Alexandru Stihi <astihi1@sheffield.ac.uk>, Chloe Hinchliffe <Chloe.Hinchliffe@newcastle.ac.uk>, Cameron Kirk <Cameron.Kirk@newcastle.ac.uk>, Björn Eskofier <bjoern.eskofier@fau.de>
License-Expression: Apache-2.0
License-File: LICENSE
License-File: NOTICE
Requires-Python: <3.14,>=3.9
Requires-Dist: intervaltree>=3.1.0
Requires-Dist: joblib>=1.3.2
Requires-Dist: numba>=0.60.0
Requires-Dist: numpy>=1.25.2
Requires-Dist: openpyxl>=3.1.2
Requires-Dist: pandas>=2.2.0
Requires-Dist: pingouin>=0.5.5
Requires-Dist: pooch>=1.8.1
Requires-Dist: python-dotenv>=1.0.1
Requires-Dist: pywavelets>=1.5.0
Requires-Dist: scikit-learn>=1.6.1
Requires-Dist: scipy>=1.11.2
Requires-Dist: seaborn>=0.12.0
Requires-Dist: statsmodels>=0.14.3
Requires-Dist: tpcp>=2.0.0
